gitlab_gemini_reviewer/__init__.py
gitlab_gemini_reviewer/gemini_mr_review.py
gitlab_gemini_reviewer-0.3.6.dist-info/METADATA
gitlab_gemini_reviewer-0.3.6.dist-info/WHEEL
gitlab_gemini_reviewer-0.3.6.dist-info/entry_points.txt
gitlab_gemini_reviewer-0.3.6.dist-info/top_level.txt
gitlab_gemini_reviewer-0.3.6.dist-info/RECORD
