Metadata-Version: 2.4
Name: gitlab-gemini-reviewer
Version: 0.3.6
Summary: A Gemini-based tool to review GitLab Merge Requests.
Author-email: Alair Junior <alairjt@gmail.com>
Project-URL: Homepage, https://github.com/alairjt/gitlab-gemini-reviewer
Project-URL: Bug Tracker, https://github.com/alairjt/gitlab-gemini-reviewer/issues
Keywords: gitlab,gemini,merge request,code review
Classifier: Programming Language :: Python :: 3
Classifier: License :: OSI Approved :: MIT License
Classifier: Operating System :: OS Independent
Requires-Python: >=3.8
Requires-Dist: google-generativeai>=0.3.0
Requires-Dist: requests>=2.28.0
Requires-Dist: python-dotenv>=1.0.0
Requires-Dist: jira==3.6.0
